resting/__init__.py
resting/client.py
resting/exceptions.py
resting/hateoas.py
resting/logger.py
resting/paginators.py
resting/resources.py
resting/settings.py
resting/utils.py
resting-0.3.6b0.dist-info/METADATA
resting-0.3.6b0.dist-info/WHEEL
resting-0.3.6b0.dist-info/top_level.txt
resting-0.3.6b0.dist-info/RECORD
